{
    "id": 25610878,
    "name": "aftermath",
    "author": "Exenity",
    "creators": ["Findexi", "Bassiegames", "Rhythmic", "Exenity", "Hinds", "knobbelboy", "Squizz", "Vultra", "Waze"],
    "verifier": "YoyiGD",
    "verification": "https://youtu.be/hAkoji9gEYQ?si=pBjmoexJxKNmd7Z0",
    "percentToQualify": "100",
    "password": "Free to Copy",
    "records": [
          {
            "user": "El Chamo GT",
            "link": "https://www.tiktok.com/@giansito44/video/7587059619260861752?is_from_webapp=1&sender_device=pc&web_id=7576853467655325196",
            "percent": 100,
            "hz": 240
        },
         {
            "user": "SoyPalala",
            "link": "https://www.youtube.com/watch?v=sEsbaZOccaQ",
            "percent": 100,
            "hz": 240
        },
        {
            "user": "Coniac",
            "link": "https://www.youtube.com/watch?v=GTeJfvCcrgc",
            "percent": 100,
            "hz": 60
        },
        {
            "user": "axds",
            "link": "",
            "percent": 100,
            "hz": 180
        },
        {
            "user": "Veriscent",
            "link": "https://youtu.be/XT_C04JohC4?si=mYVkXKD0jKNV6Hr5",
            "percent": 100,
            "hz": 240
        },
        {
            "user": "GW",
            "link": "https://youtu.be/GcN8EE9V5N0?si=SRqKP_NPRiI6E56J",
            "percent": 100,
            "hz": 240
        },
        {
            "user": "Moochie",
            "link": "https://youtu.be/etAwKxVqvy8?si=j-Et-Gw4_ivS0SL8",
            "percent": 100,
            "hz": 240
        }
        
    ]
}
