{
    "id": 54615662,
    "name": "The Yandere",
    "author": "Dorami",
    "creators": ["Osiris GD", "Alkali", "MrLorenzo", "FarDreamer", "Dorami", "CastriX", "DanZmeN", "Jghost", "Elisione", "MikeWheelerFan", "REDACTED", "YunHaSeu14", "JonathanGD", "Bransilver", "Spectex", "Partition", "I'm Master X", "Alderite", "DavJT", "MulpanMazl"],
    "verifier": "Veriscent",
    "verification": "https://www.youtube.com/watch?v=0iDUH4OzlLM",
    "percentToQualify": "58",
    "password": "Free To Copy",
    "records": [
    ]
}
